{
  "id": "6-4",
  "subtitle": "Demon Current",
  "objective": "Reach the Goal",
  "theme": "abyssal-hollow",
  "rankTargets": {
    "sTime": 56,
    "aTime": 78,
    "bTime": 110,
    "cTime": 150
  },
  "world": {
    "width": 12000,
    "height": 1080,
    "tileSize": 64
  },
  "playerSpawn": {
    "x": 256,
    "surfaceY": 704
  },
  "platforms": [
    {
      "col": 2,
      "row": 11,
      "width": 12,
      "height": 1
    },
    {
      "col": 23,
      "row": 10,
      "width": 6,
      "height": 1
    },
    {
      "col": 40,
      "row": 8,
      "width": 6,
      "height": 1
    },
    {
      "col": 58,
      "row": 7,
      "width": 6,
      "height": 1
    },
    {
      "col": 78,
      "row": 9,
      "width": 7,
      "height": 1
    },
    {
      "col": 99,
      "row": 11,
      "width": 8,
      "height": 1
    },
    {
      "col": 120,
      "row": 9,
      "width": 7,
      "height": 1
    },
    {
      "col": 142,
      "row": 8,
      "width": 7,
      "height": 1
    },
    {
      "col": 164,
      "row": 10,
      "width": 14,
      "height": 1
    }
  ],
  "movingPlatforms": [
    {
      "id": "demon-lift-a",
      "col": 17,
      "row": 10,
      "width": 4,
      "height": 1,
      "axis": "y",
      "distance": 180,
      "durationMs": 2500,
      "phase": 0.2
    },
    {
      "id": "demon-ferry-a",
      "col": 90,
      "row": 10,
      "width": 4,
      "height": 1,
      "axis": "x",
      "distance": 420,
      "durationMs": 3100,
      "phase": 0.5
    },
    {
      "id": "demon-lift-b",
      "col": 153,
      "row": 9,
      "width": 4,
      "height": 1,
      "axis": "y",
      "distance": 180,
      "durationMs": 2600,
      "phase": 0.65
    }
  ],
  "hazards": [
    {
      "id": "current-spike-a",
      "type": "spikes",
      "x": 1500,
      "surfaceY": 704,
      "width": 220,
      "height": 72,
      "orientation": "floor"
    },
    {
      "id": "current-lava-a",
      "type": "lava",
      "x": 2920,
      "surfaceY": 640,
      "width": 260,
      "height": 78
    },
    {
      "id": "current-spike-b",
      "type": "spikes",
      "x": 4500,
      "surfaceY": 512,
      "width": 220,
      "height": 72,
      "orientation": "floor"
    },
    {
      "id": "current-lava-b",
      "type": "lava",
      "x": 6400,
      "surfaceY": 704,
      "width": 260,
      "height": 78
    },
    {
      "id": "current-spike-c",
      "type": "spikes",
      "x": 8000,
      "surfaceY": 576,
      "width": 220,
      "height": 72,
      "orientation": "floor"
    },
    {
      "id": "current-lava-c",
      "type": "lava",
      "x": 10300,
      "surfaceY": 640,
      "width": 260,
      "height": 78
    }
  ],
  "gravityZones": [
    {
      "id": "current-up-a",
      "x": 2450,
      "y": 0,
      "width": 2600,
      "height": 1080,
      "direction": "up"
    },
    {
      "id": "current-down-a",
      "x": 5050,
      "y": 0,
      "width": 2300,
      "height": 1080,
      "direction": "down"
    },
    {
      "id": "current-up-b",
      "x": 7350,
      "y": 0,
      "width": 2500,
      "height": 1080,
      "direction": "up"
    },
    {
      "id": "current-down-b",
      "x": 9850,
      "y": 0,
      "width": 2200,
      "height": 1080,
      "direction": "down"
    }
  ],
  "surfaceZones": [
    {
      "id": "current-ice",
      "type": "ice",
      "x": 5200,
      "y": 0,
      "width": 3400,
      "height": 1080
    }
  ],
  "coins": [
    {
      "x": 420,
      "y": 648
    },
    {
      "x": 1200,
      "y": 620
    },
    {
      "x": 2050,
      "y": 540
    },
    {
      "x": 3200,
      "y": 390
    },
    {
      "x": 4500,
      "y": 330
    },
    {
      "x": 5900,
      "y": 520
    },
    {
      "x": 7200,
      "y": 620
    },
    {
      "x": 8500,
      "y": 500
    },
    {
      "x": 9800,
      "y": 390
    },
    {
      "x": 11100,
      "y": 584
    }
  ],
  "enemies": [
    {
      "id": "current-guard-a",
      "x": 560,
      "surfaceY": 704,
      "patrolMinX": 320,
      "patrolMaxX": 760
    },
    {
      "id": "current-core-a",
      "type": "azure-core",
      "respawnPolicy": "regenerate",
      "countsForScore": false,
      "x": 3200,
      "y": 390,
      "patrolMinX": 3200,
      "patrolMaxX": 3200
    },
    {
      "id": "current-core-b",
      "type": "azure-core",
      "respawnPolicy": "regenerate",
      "countsForScore": false,
      "x": 5900,
      "y": 500,
      "patrolMinX": 5900,
      "patrolMaxX": 5900
    },
    {
      "id": "current-guard-b",
      "x": 6500,
      "surfaceY": 704,
      "patrolMinX": 6350,
      "patrolMaxX": 6900
    },
    {
      "id": "current-core-c",
      "type": "azure-core",
      "respawnPolicy": "regenerate",
      "countsForScore": false,
      "x": 9800,
      "y": 390,
      "patrolMinX": 9800,
      "patrolMaxX": 9800
    },
    {
      "id": "current-guard-c",
      "x": 10800,
      "surfaceY": 640,
      "patrolMinX": 10550,
      "patrolMaxX": 11250
    }
  ],
  "checkpoints": [
    {
      "id": "current-high-check",
      "x": 3850,
      "surfaceY": 448,
      "spawnX": 3870,
      "spawnSurfaceY": 448,
      "spawnGravity": "up"
    },
    {
      "id": "current-exit-check",
      "x": 10800,
      "surfaceY": 640,
      "spawnX": 10820,
      "spawnSurfaceY": 640
    }
  ],
  "sections": [
    {
      "id": "updraft-lift",
      "startX": 0,
      "endX": 3900,
      "purpose": "Combine lift with gravity inversion."
    },
    {
      "id": "ice-current",
      "startX": 3900,
      "endX": 8500,
      "purpose": "Slide while gravity zones alternate."
    },
    {
      "id": "demon-exit",
      "startX": 8500,
      "endX": 12000,
      "purpose": "Final mixed trap route."
    }
  ],
  "goal": {
    "x": 11000,
    "surfaceY": 640
  }
}
